rs2py-0.1.4.dist-info/METADATA
rs2py-0.1.4.dist-info/WHEEL
rs2py/__init__.py
rs2py/rs2py.pyd
rs2py-0.1.4.dist-info/RECORD
